awslambda/__init__.py
awslambda/api_helper.py
awslambda/awslambda_client.py
awslambda/configuration.py
awslambda/controllers/__init__.py
awslambda/controllers/account_settings_controller.py
awslambda/controllers/alias_controller.py
awslambda/controllers/aliases_controller.py
awslambda/controllers/async_controller.py
awslambda/controllers/base_controller.py
awslambda/controllers/event_source_mapping_controller.py
awslambda/controllers/function_code_controller.py
awslambda/controllers/function_concurrency_controller.py
awslambda/controllers/function_configuration_controller.py
awslambda/controllers/function_controller.py
awslambda/controllers/layer_version_by_arn_controller.py
awslambda/controllers/layer_version_controller.py
awslambda/controllers/layer_version_permission_controller.py
awslambda/controllers/layer_version_policy_controller.py
awslambda/controllers/layers_controller.py
awslambda/controllers/misc_controller.py
awslambda/controllers/permission_controller.py
awslambda/controllers/policy_controller.py
awslambda/controllers/resource_controller.py
awslambda/controllers/tags_controller.py
awslambda/controllers/version_controller.py
awslambda/controllers/versions_by_function_controller.py
awslambda/exceptions/__init__.py
awslambda/exceptions/api_exception.py
awslambda/http/__init__.py
awslambda/http/http_call_back.py
awslambda/http/http_method_enum.py
awslambda/http/http_request.py
awslambda/http/http_response.py
awslambda/models/__init__.py
awslambda/utilities/__init__.py
awslambda/utilities/file_wrapper.py
sdl_aws_lambda-1.0.0.dist-info/licenses/LICENSE
sdl_aws_lambda-1.0.0.dist-info/METADATA
sdl_aws_lambda-1.0.0.dist-info/WHEEL
sdl_aws_lambda-1.0.0.dist-info/top_level.txt
sdl_aws_lambda-1.0.0.dist-info/RECORD
